evento/__init__.py
evento/async_event.py
evento/base.py
evento/decorators.py
evento/event.py
evento/signature.py
evento-2.0.1.dist-info/LICENSE
evento-2.0.1.dist-info/WHEEL
evento-2.0.1.dist-info/METADATA
evento-2.0.1.dist-info/RECORD
