Metadata-Version: 2.1
Name: evento
Version: 2.0.1
Summary: Observer pattern made muy facil
Home-page: https://github.com/markkorput/pyevento
License: MIT
Author: Mark van de Korput
Author-email: dr.theman@gmail.com
Requires-Python: >=3.10,<4.0
Classifier: License :: OSI Approved :: MIT License
Classifier: Programming Language :: Python :: 3
Classifier: Programming Language :: Python :: 3.10
Project-URL: Repository, https://github.com/markkorput/pyevento
